{
  "gitSyncId": "673cb4ff829f7b3535096676_3911c748-96a2-4eec-ad35-4a917deb9076",
  "id": "Directions_JSObject1.tryGetLocation",
  "pluginId": "js-plugin",
  "pluginType": "JS",
  "unpublishedAction": {
    "actionConfiguration": {
      "encodeParamsToggle": true,
      "isAsync": true,
      "jsArguments": [],
      "paginationType": "NONE",
      "timeoutInMillisecond": 10000
    },
    "collectionId": "Directions_JSObject1",
    "confirmBeforeExecute": false,
    "datasource": {
      "isAutoGenerated": false,
      "name": "UNUSED_DATASOURCE",
      "pluginId": "js-plugin"
    },
    "dynamicBindingPathList": [
      {
        "key": "body"
      }
    ],
    "executeOnLoad": true,
    "fullyQualifiedName": "JSObject1.tryGetLocation",
    "name": "tryGetLocation",
    "pageId": "Directions",
    "userSetOnLoad": true
  }
}